pysatCDF-0.3.1.dist-info/RECORD
pysatCDF-0.3.1.dist-info/LICENSE
pysatCDF-0.3.1.dist-info/WHEEL
pysatCDF-0.3.1.dist-info/top_level.txt
pysatCDF-0.3.1.dist-info/METADATA
pysatCDF/__init__.py
pysatCDF/fortran_cdf.cpython-37m-darwin.so
pysatCDF/_cdf.py
pysatCDF/include/cdflib64.h
pysatCDF/include/cdflib.h
pysatCDF/include/cdf.inc
pysatCDF/include/cdfconfig.h
pysatCDF/include/cdfdist.h
pysatCDF/include/cdf.h
pysatCDF/.dylibs/libgfortran.5.dylib
pysatCDF/.dylibs/libquadmath.0.dylib
pysatCDF/.dylibs/libgcc_s.1.dylib
pysatCDF/lib/libcdf.a
