Metadata-Version: 1.1
Name: pysatCDF
Version: 0.3.1
Summary: Simple NASA Common Data Format (CDF) File reader.
Home-page: http://github.com/rstoneback/pysatCDF
Author: Russell Stoneback
Author-email: rstoneba@utdallas.edu
License: BSD
Platform: UNKNOWN
Classifier: Development Status :: 4 - Beta
Classifier: Intended Audience :: Science/Research
Classifier: Topic :: Scientific/Engineering :: Astronomy
Classifier: Topic :: Scientific/Engineering :: Physics
Classifier: Topic :: Scientific/Engineering :: Atmospheric Science
Classifier: License :: OSI Approved :: BSD License
Classifier: Programming Language :: Python :: 2.7
Classifier: Programming Language :: Python :: 3.4
Classifier: Programming Language :: Python :: 3.5
Classifier: Programming Language :: Python :: 3.6
